odoo/addons/base_external_dbsource_sqlite/README.rst
odoo/addons/base_external_dbsource_sqlite/__init__.py
odoo/addons/base_external_dbsource_sqlite/__manifest__.py
odoo/addons/base_external_dbsource_sqlite/demo/base_external_dbsource.xml
odoo/addons/base_external_dbsource_sqlite/i18n/base_external_dbsource_sqlite.pot
odoo/addons/base_external_dbsource_sqlite/i18n/de.po
odoo/addons/base_external_dbsource_sqlite/i18n/es.po
odoo/addons/base_external_dbsource_sqlite/i18n/hr.po
odoo/addons/base_external_dbsource_sqlite/i18n/nl_NL.po
odoo/addons/base_external_dbsource_sqlite/i18n/pt_BR.po
odoo/addons/base_external_dbsource_sqlite/i18n/sl.po
odoo/addons/base_external_dbsource_sqlite/i18n/tr.po
odoo/addons/base_external_dbsource_sqlite/models/__init__.py
odoo/addons/base_external_dbsource_sqlite/models/base_external_dbsource.py
odoo/addons/base_external_dbsource_sqlite/readme/CONFIGURE.rst
odoo/addons/base_external_dbsource_sqlite/readme/CONTRIBUTORS.rst
odoo/addons/base_external_dbsource_sqlite/readme/DESCRIPTION.rst
odoo/addons/base_external_dbsource_sqlite/readme/INSTALL.rst
odoo/addons/base_external_dbsource_sqlite/readme/ROADMAP.rst
odoo/addons/base_external_dbsource_sqlite/readme/USAGE.rst
odoo/addons/base_external_dbsource_sqlite/static/description/icon.png
odoo/addons/base_external_dbsource_sqlite/static/description/index.html
odoo/addons/base_external_dbsource_sqlite/tests/__init__.py
odoo/addons/base_external_dbsource_sqlite/tests/test_base_external_dbsource.py
odoo12_addon_base_external_dbsource_sqlite-12.0.1.0.1.dist-info/METADATA
odoo12_addon_base_external_dbsource_sqlite-12.0.1.0.1.dist-info/WHEEL
odoo12_addon_base_external_dbsource_sqlite-12.0.1.0.1.dist-info/top_level.txt
odoo12_addon_base_external_dbsource_sqlite-12.0.1.0.1.dist-info/RECORD
